lennybot/__init__.py
lennybot/__main__.py
lennybot/lennybot.py
lennybot/actions/__init__.py
lennybot/actions/download_resources.py
lennybot/actions/iaction.py
lennybot/actions/remove_checksums.py
lennybot/actions/update_dockerfile.py
lennybot/actions/update_image_tag.py
lennybot/actions/update_json.py
lennybot/actions/update_yaml.py
lennybot/check/__init__.py
lennybot/check/docker_image_available.py
lennybot/check/icheck.py
lennybot/config/__init__.py
lennybot/config/config.py
lennybot/helper/__init__.py
lennybot/model/__init__.py
lennybot/model/plan.py
lennybot/model/state.py
lennybot/service/__init__.py
lennybot/service/apply.py
lennybot/service/github.py
lennybot/service/plan.py
lennybot/service/source/__init__.py
lennybot/service/source/isource.py
lennybot/service/source/source_github.py
lennybot/service/source/source_github_query.py
lennybot/service/source/source_nodejs.py
lennybot-1.0.32.data/data/generic/README.md
lennybot-1.0.32.data/data/generic/requirements.txt
lennybot-1.0.32.data/data/generic/version.txt
lennybot-1.0.32.dist-info/LICENSE
lennybot-1.0.32.dist-info/METADATA
lennybot-1.0.32.dist-info/WHEEL
lennybot-1.0.32.dist-info/entry_points.txt
lennybot-1.0.32.dist-info/top_level.txt
lennybot-1.0.32.dist-info/RECORD
