Metadata-Version: 2.1
Name: lennybot
Version: 1.0.32
Summary: Automatic Updates for Kustomize Resources
Home-page: http://github.com/raynigon/lennybot
Author: Simon Schneider
Author-email: dev@raynigon.com
Project-URL: Bug Reports, https://github.com/raynigon/lennybot/issues
Project-URL: Source, https://github.com/raynigon/lennybot/
Keywords: kustomize
Classifier: Development Status :: 4 - Beta
Classifier: Programming Language :: Python :: 3.6
Classifier: Programming Language :: Python :: 3.7
Classifier: Programming Language :: Python :: 3.8
Classifier: Programming Language :: Python :: 3.9
Classifier: License :: OSI Approved :: Apache Software License
Classifier: Operating System :: OS Independent
Requires-Python: >=3.6, <4
License-File: LICENSE
Requires-Dist: pyyaml
Requires-Dist: yamlpath
Requires-Dist: requests
Requires-Dist: GitPython
Requires-Dist: PyGithub
Requires-Dist: jsonpath-ng
Provides-Extra: dev
Requires-Dist: setuptools ; extra == 'dev'
Requires-Dist: wheel ; extra == 'dev'
Requires-Dist: black ; extra == 'dev'
Provides-Extra: test
Requires-Dist: coverage ; extra == 'test'
Requires-Dist: pytest ; extra == 'test'
